nrewebservices/__init__.py
nrewebservices/__release__.py
nrewebservices/__version__.py
nrewebservices/common/__init__.py
nrewebservices/common/soap.py
nrewebservices/ldbws/__init__.py
nrewebservices/ldbws/responses.py
nrewebservices/ldbws/webservice.py
nrewebservices-0.2.1.dist-info/LICENSE
nrewebservices-0.2.1.dist-info/METADATA
nrewebservices-0.2.1.dist-info/WHEEL
nrewebservices-0.2.1.dist-info/top_level.txt
nrewebservices-0.2.1.dist-info/RECORD
